mcvqoe/accesstime/__init__.py
mcvqoe/accesstime/access_time.py
mcvqoe/accesstime/access_time_eval.py
mcvqoe/accesstime/access_time_hw_test.py
mcvqoe/accesstime/access_time_sim.py
mcvqoe/accesstime/version.py
mcvqoe/accesstime/audio_clips/F1_b9_w1_bed.csv
mcvqoe/accesstime/audio_clips/F1_b9_w1_bed.wav
mcvqoe/accesstime/audio_clips/F3_b31_w2_law.csv
mcvqoe/accesstime/audio_clips/F3_b31_w2_law.wav
mcvqoe/accesstime/audio_clips/M3_b38_w1_hang.csv
mcvqoe/accesstime/audio_clips/M3_b38_w1_hang.wav
mcvqoe/accesstime/audio_clips/M4_b14_w1_not.csv
mcvqoe/accesstime/audio_clips/M4_b14_w1_not.wav
mcvqoe/accesstime/correction_data/Tx_F1_b9_w1_bed.csv
mcvqoe/accesstime/correction_data/Tx_F3_b31_w2_law.csv
mcvqoe/accesstime/correction_data/Tx_M3_b38_w1_hang.csv
mcvqoe/accesstime/correction_data/Tx_M4_b14_w1_not.csv
mcvqoe/accesstime/correction_data/capture_PTT-gate_14-May-2021_07-30-20_F1_b9_w1_bed.csv
mcvqoe/accesstime/correction_data/capture_PTT-gate_14-May-2021_07-30-20_F3_b31_w2_law.csv
mcvqoe/accesstime/correction_data/capture_PTT-gate_14-May-2021_07-30-20_M3_b38_w1_hang.csv
mcvqoe/accesstime/correction_data/capture_PTT-gate_14-May-2021_07-30-20_M4_b14_w1_not.csv
mcvqoe_accesstime-2.2.3.dist-info/LICENSE.md
mcvqoe_accesstime-2.2.3.dist-info/METADATA
mcvqoe_accesstime-2.2.3.dist-info/WHEEL
mcvqoe_accesstime-2.2.3.dist-info/entry_points.txt
mcvqoe_accesstime-2.2.3.dist-info/top_level.txt
mcvqoe_accesstime-2.2.3.dist-info/RECORD
